README
setup.py
ptools/__init__.py
ptools/current.py
ptools/linux.py
ptools/win.py
ptools.egg-info/PKG-INFO
ptools.egg-info/SOURCES.txt
ptools.egg-info/dependency_links.txt
ptools.egg-info/top_level.txt