Metadata-Version: 1.0
Name: ptools
Version: 1.0b3
Summary: Cross Platform Process Infomation (cmdline, environ) and Management
Home-page: https://github.com/tonysimpson/ptools
Author: Tony Simpson
Author-email: tony.simpson@thetestpeople.com
License: MIT
Platform: UNKNOWN
